{
   "has_many" : {
      "fetch" : 0
   },
   "might_have" : {
      "fetch" : 0
   },
   "belongs_to" : {
      "fetch" : 0
   },
   "sets" : [
      {
         "quantity" : "all",
         "class" : "Login"
      },
      {
         "quantity" : "all",
         "class" : "OLCModule"
      },
      {
         "quantity" : "all",
         "class" : "OLCModulePageLink"
      },
      {
         "quantity" : "all",
         "class" : "Qualification"
      },
      {
         "quantity" : "all",
         "class" : "OLCCourse"
      },
      {
         "quantity" : "all",
         "class" : "OLCPage"
      },
      {
         "quantity" : "all",
         "class" : "Course"
      },
      {
         "class" : "Professional",
         "quantity" : "all"
      },
      {
         "class" : "OLCStudent",
         "quantity" : "all"
      },
      {
         "class" : "PremiumAuthorisation",
         "quantity" : "all"
      },
      {
         "class" : "CourseType",
         "quantity" : "all"
      },
      {
         "class" : "PremiumCookieLog",
         "quantity" : "all"
      },
      {
         "class" : "OLCCourseModuleLink",
         "quantity" : "all"
      },
      {
         "quantity" : "all",
         "class" : "Session"
      },
      {
         "quantity" : "all",
         "class" : "Profile"
      },
      {
         "quantity" : "all",
         "class" : "Enquiry"
      },
      {
         "class" : "InstructorQualification",
         "quantity" : "all"
      },
      {
         "class" : "InstructorCourse",
         "quantity" : "all"
      },
      {
         "quantity" : "all",
         "class" : "Audit"
      },
      {
         "quantity" : "all",
         "class" : "OLCComponent"
      }
   ]
}
